Metadata-Version: 2.1
Name: csgo-cheats
Version: 1.9
Summary: A python package that imports CSGO Cheats
Home-page: UNKNOWN
Author: giant_tiger
Author-email: anonymousrandyboy@gmail.com
License: UNKNOWN
Platform: UNKNOWN
